mortis/__init__.py
mortis/globcfg.py
mortis/utils.py
mortis/aff/__init__.py
mortis/aff/aff.py
mortis/aff/timinggroup.py
mortis/aff/events/__init__.py
mortis/aff/events/arc.py
mortis/aff/events/camera.py
mortis/aff/events/hold.py
mortis/aff/events/scenecontrol.py
mortis/aff/events/tap.py
mortis/aff/events/timing.py
mortis/aff/lexer/__init__.py
mortis/aff/lexer/analyse.py
mortis/aff/lexer/token.py
mortis/aff/types/__init__.py
mortis/aff/types/coord.py
mortis/aff/types/dffloat.py
mortis/aff/types/easings.py
mortis/aff/types/hitsound_str.py
mortis/aff/types/models.py
mortis/songlist/__init__.py
mortis/songlist/base.py
mortis/songlist/diffs.py
mortis/songlist/item.py
mortis/songlist/types.py
mortis-0.3.1.dist-info/licenses/LICENSE
mortis-0.3.1.dist-info/METADATA
mortis-0.3.1.dist-info/WHEEL
mortis-0.3.1.dist-info/top_level.txt
mortis-0.3.1.dist-info/RECORD
