Metadata-Version: 2.4
Name: mortis
Version: 0.3.1
Summary: Utils for Arcaea files.
Author-email: IzayoiArika <1975516551@qq.com>
Project-URL: homepage, https://github.com/IzayoiArika/mortis
Classifier: Programming Language :: Python :: 3
Classifier: Programming Language :: Python :: 3.12
Classifier: License :: OSI Approved :: GNU General Public License v3 (GPLv3)
Classifier: Operating System :: OS Independent
Classifier: Typing :: Typed
Requires-Python: >=3.12
License-File: LICENSE
Requires-Dist: pydantic>=2.12.0
Dynamic: license-file
